pglock/__init__.py
pglock/config.py
pglock/core.py
pglock/management/__init__.py
pglock/management/commands/__init__.py
pglock/management/commands/pglock.py
pglock/models.py
pglock/py.typed
pglock/utils.py
pglock/version.py
django_pglock-1.7.2.dist-info/LICENSE
django_pglock-1.7.2.dist-info/METADATA
django_pglock-1.7.2.dist-info/WHEEL
django_pglock-1.7.2.dist-info/RECORD
