Metadata-Version: 2.1
Name: django-pglock
Version: 1.7.2
Summary: Postgres locking routines and lock table access.
Home-page: https://github.com/AmbitionEng/django-pglock
License: BSD-3-Clause
Author: Wes Kendall
Requires-Python: >=3.9.0,<4
Classifier: Framework :: Django
Classifier: Framework :: Django :: 4.2
Classifier: Framework :: Django :: 5.0
Classifier: Framework :: Django :: 5.1
Classifier: Intended Audience :: Developers
Classifier: License :: OSI Approved :: BSD License
Classifier: Operating System :: OS Independent
Classifier: Programming Language :: Python
Classifier: Programming Language :: Python :: 3
Classifier: Programming Language :: Python :: 3.9
Classifier: Programming Language :: Python :: 3.10
Classifier: Programming Language :: Python :: 3.11
Classifier: Programming Language :: Python :: 3.12
Classifier: Programming Language :: Python :: 3.13
Classifier: Programming Language :: Python :: 3 :: Only
Requires-Dist: django (>=4)
Requires-Dist: django-pgactivity (>=1.2,<2)
Project-URL: Documentation, https://django-pglock.readthedocs.io
Project-URL: Repository, https://github.com/AmbitionEng/django-pglock
